{
	"_id": {
		"$oid": "6096a395f5a1530016aef430"
	},
	"ingredient_id": "71WYhFHDi",
	"category": "Pouchong",
	"category_id": "vvecAwA8n",
	"name": "Aginamoto MSG",
	"unit_id": "qkmUzGwng",
	"unit": "gm",
	"createdOn": {
		"$date": "2021-05-08T14:43:33Z"
	},
	"__v": 0,
	"stock": -9060
}
{
	"_id": {
		"$oid": "6096a3bcf5a1530016aef431"
	},
	"ingredient_id": "6b6zZvDTF",
	"category": "Fish",
	"category_id": "nwfim3VxF",
	"name": "Asian Seabass Fish",
	"unit_id": "qkmUzGwng",
	"unit": "gm",
	"createdOn": {
		"$date": "2021-05-08T14:44:12Z"
	},
	"__v": 0,
	"stock": -61316
}
{
	"_id": {
		"$oid": "6096a3daf5a1530016aef432"
	},
	"ingredient_id": "15gd0teBR",
	"category": "Vegetables",
	"category_id": "qrv8oa3rz",
	"name": "Babycorn",
	"unit_id": "qkmUzGwng",
	"unit": "gm",
	"createdOn": {
		"$date": "2021-05-08T14:44:42Z"
	},
	"__v": 0,
	"stock": -17520
}
{
	"_id": {
		"$oid": "6096a3f2f5a1530016aef433"
	},
	"ingredient_id": "_8J1zwCN0",
	"category": "Vegetables",
	"category_id": "qrv8oa3rz",
	"name": "Beans",
	"unit_id": "qkmUzGwng",
	"unit": "gm",
	"createdOn": {
		"$date": "2021-05-08T14:45:06Z"
	},
	"__v": 0,
	"stock": -3025
}
{
	"_id": {
		"$oid": "6096a415f5a1530016aef434"
	},
	"ingredient_id": "pje_R6gzz",
	"category": "Grocery",
	"category_id": "n3YT3gSBz",
	"name": "Beuli Dal",
	"unit_id": "qkmUzGwng",
	"unit": "gm",
	"createdOn": {
		"$date": "2021-05-08T14:45:41Z"
	},
	"__v": 0,
	"stock": -7800
}
{
	"_id": {
		"$oid": "6096a42ff5a1530016aef435"
	},
	"ingredient_id": "FsPQerWF3",
	"category": "Spices",
	"category_id": "rbuHbetmO",
	"name": "Black Pepper Powder",
	"unit_id": "qkmUzGwng",
	"unit": "gm",
	"createdOn": {
		"$date": "2021-05-08T14:46:07Z"
	},
	"__v": 0,
	"stock": -17208
}
{
	"_id": {
		"$oid": "6096a446f5a1530016aef436"
	},
	"ingredient_id": "pDikNWZeV",
	"category": "Spices",
	"category_id": "rbuHbetmO",
	"name": "Black Pepper Whole",
	"unit_id": "qkmUzGwng",
	"unit": "gm",
	"createdOn": {
		"$date": "2021-05-08T14:46:30Z"
	},
	"__v": 0,
	"stock": 250
}
{
	"_id": {
		"$oid": "6096a45cf5a1530016aef437"
	},
	"ingredient_id": "9boediBKY",
	"category": "Spices",
	"category_id": "rbuHbetmO",
	"name": "Black Salt",
	"unit_id": "qkmUzGwng",
	"unit": "gm",
	"createdOn": {
		"$date": "2021-05-08T14:46:52Z"
	},
	"__v": 0,
	"stock": -2960
}
{
	"_id": {
		"$oid": "6096a476f5a1530016aef438"
	},
	"ingredient_id": "AhxDPaaUl",
	"category": "Grocery",
	"category_id": "n3YT3gSBz",
	"name": "Baking Powder",
	"unit_id": "qkmUzGwng",
	"unit": "gm",
	"createdOn": {
		"$date": "2021-05-08T14:47:18Z"
	},
	"__v": 0,
	"stock": -26018
}
{
	"_id": {
		"$oid": "6096a48af5a1530016aef439"
	},
	"ingredient_id": "HsSUfoM_M",
	"category": "Vegetables",
	"category_id": "qrv8oa3rz",
	"name": "Brocolli",
	"unit_id": "qkmUzGwng",
	"unit": "gm",
	"createdOn": {
		"$date": "2021-05-08T14:47:38Z"
	},
	"__v": 0,
	"stock": 0
}
{
	"_id": {
		"$oid": "6096a9d6f5a1530016aef44a"
	},
	"ingredient_id": "P7CQ6yfrH",
	"category": "xDairy",
	"category_id": "qbZmJuFpV",
	"name": "Butter",
	"unit_id": "qkmUzGwng",
	"unit": "gm",
	"createdOn": {
		"$date": "2021-05-08T15:10:14Z"
	},
	"__v": 0,
	"stock": -19030
}
{
	"_id": {
		"$oid": "6096a9e5f5a1530016aef44b"
	},
	"ingredient_id": "9DXWBnrZe",
	"category": "Vegetables",
	"category_id": "qrv8oa3rz",
	"name": "Cabbage",
	"unit_id": "qkmUzGwng",
	"unit": "gm",
	"createdOn": {
		"$date": "2021-05-08T15:10:29Z"
	},
	"__v": 0,
	"stock": 13970
}
{
	"_id": {
		"$oid": "6096a9f5f5a1530016aef44c"
	},
	"ingredient_id": "b0SNixqKq",
	"category": "Pouchong",
	"category_id": "vvecAwA8n",
	"name": "Canned Mushroom",
	"unit_id": "qkmUzGwng",
	"unit": "gm",
	"createdOn": {
		"$date": "2021-05-08T15:10:45Z"
	},
	"__v": 0,
	"stock": 0
}
{
	"_id": {
		"$oid": "6096aa08f5a1530016aef44d"
	},
	"ingredient_id": "9EzwzObTF",
	"category": "Pouchong",
	"category_id": "vvecAwA8n",
	"name": "Capsicum Sauce",
	"unit_id": "qkmUzGwng",
	"unit": "gm",
	"createdOn": {
		"$date": "2021-05-08T15:11:04Z"
	},
	"__v": 0,
	"stock": 500
}
{
	"_id": {
		"$oid": "6096aa1af5a1530016aef44e"
	},
	"ingredient_id": "PLvlfBfMj",
	"category": "Vegetables",
	"category_id": "qrv8oa3rz",
	"name": "Carrot",
	"unit_id": "qkmUzGwng",
	"unit": "gm",
	"createdOn": {
		"$date": "2021-05-08T15:11:22Z"
	},
	"__v": 0,
	"stock": 4945
}
{
	"_id": {
		"$oid": "6096aa31f5a1530016aef44f"
	},
	"ingredient_id": "B2HIVLuRE",
	"category": "Vegetables",
	"category_id": "qrv8oa3rz",
	"name": "Celery Leaf",
	"unit_id": "qkmUzGwng",
	"unit": "gm",
	"createdOn": {
		"$date": "2021-05-08T15:11:45Z"
	},
	"__v": 0,
	"stock": -90
}
{
	"_id": {
		"$oid": "6096aa5bf5a1530016aef450"
	},
	"ingredient_id": "XlW_wsZPX",
	"category": "Spices",
	"category_id": "rbuHbetmO",
	"name": "Chaat Masala",
	"unit_id": "qkmUzGwng",
	"unit": "gm",
	"createdOn": {
		"$date": "2021-05-08T15:12:27Z"
	},
	"__v": 0,
	"stock": -27640
}
{
	"_id": {
		"$oid": "6096aaeff5a1530016aef451"
	},
	"ingredient_id": "3cIKVVMxz",
	"category": "Grocery",
	"category_id": "n3YT3gSBz",
	"name": "Chana Dal",
	"unit_id": "qkmUzGwng",
	"unit": "gm",
	"createdOn": {
		"$date": "2021-05-08T15:14:55Z"
	},
	"__v": 0,
	"stock": -7800
}
{
	"_id": {
		"$oid": "6096ab05f5a1530016aef452"
	},
	"ingredient_id": "nT5lXJADg",
	"category": "xDairy",
	"category_id": "qbZmJuFpV",
	"name": "Cheese",
	"unit_id": "qkmUzGwng",
	"unit": "gm",
	"createdOn": {
		"$date": "2021-05-08T15:15:17Z"
	},
	"__v": 0,
	"stock": -9210
}
{
	"_id": {
		"$oid": "6096ab1ef5a1530016aef453"
	},
	"ingredient_id": "OjTTky0PH",
	"category": "Poultry",
	"category_id": "ym2_N2UNX",
	"name": "Chicken Breast Boneless",
	"unit_id": "qkmUzGwng",
	"unit": "gm",
	"createdOn": {
		"$date": "2021-05-08T15:15:42Z"
	},
	"__v": 0,
	"stock": -504210
}
{
	"_id": {
		"$oid": "6096ab3df5a1530016aef454"
	},
	"ingredient_id": "je3vUltfC",
	"category": "Poultry",
	"category_id": "ym2_N2UNX",
	"name": "Egg",
	"unit_id": "-cf60bJYu",
	"unit": "pc",
	"createdOn": {
		"$date": "2021-05-08T15:16:13Z"
	},
	"__v": 0,
	"stock": -14968.83999999995
}
{
	"_id": {
		"$oid": "6096ababf5a1530016aef456"
	},
	"ingredient_id": "FOaHKCA1y",
	"category": "Pouchong",
	"category_id": "vvecAwA8n",
	"name": "Tomato Sauce",
	"unit_id": "qkmUzGwng",
	"unit": "gm",
	"createdOn": {
		"$date": "2021-05-08T15:18:03Z"
	},
	"__v": 0,
	"stock": -83867
}
{
	"_id": {
		"$oid": "609cdb187df9360016fe04d7"
	},
	"ingredient_id": "Tx4Zz7dsd",
	"category": "Poultry",
	"category_id": "ym2_N2UNX",
	"name": "Chicken Leg Boneless",
	"unit_id": "qkmUzGwng",
	"unit": "gm",
	"createdOn": {
		"$date": "2021-05-13T07:54:00Z"
	},
	"__v": 0,
	"stock": -235300
}
{
	"_id": {
		"$oid": "609cdb287df9360016fe04d8"
	},
	"ingredient_id": "puKlrwe67",
	"category": "Poultry",
	"category_id": "ym2_N2UNX",
	"name": "Chicken Whole",
	"unit_id": "qkmUzGwng",
	"unit": "gm",
	"createdOn": {
		"$date": "2021-05-13T07:54:16Z"
	},
	"__v": 0,
	"stock": -236060
}
{
	"_id": {
		"$oid": "609cdb3d7df9360016fe04d9"
	},
	"ingredient_id": "inzcyeUeS",
	"category": "Poultry",
	"category_id": "ym2_N2UNX",
	"name": "Chicken Wings",
	"unit_id": "qkmUzGwng",
	"unit": "gm",
	"createdOn": {
		"$date": "2021-05-13T07:54:37Z"
	},
	"__v": 0,
	"stock": 21750
}
{
	"_id": {
		"$oid": "609cdb677df9360016fe04da"
	},
	"ingredient_id": "4c1LVednX",
	"category": "Spices",
	"category_id": "rbuHbetmO",
	"name": "Chilli Powder",
	"unit_id": "qkmUzGwng",
	"unit": "gm",
	"createdOn": {
		"$date": "2021-05-13T07:55:19Z"
	},
	"__v": 0,
	"stock": -820
}
{
	"_id": {
		"$oid": "609cdba57df9360016fe04db"
	},
	"ingredient_id": "M9KbCnG1O",
	"category": "Vegetables",
	"category_id": "qrv8oa3rz",
	"name": "Chinese Cabbage",
	"unit_id": "qkmUzGwng",
	"unit": "gm",
	"createdOn": {
		"$date": "2021-05-13T07:56:21Z"
	},
	"__v": 0,
	"stock": 0
}
{
	"_id": {
		"$oid": "609cdbce7df9360016fe04dc"
	},
	"ingredient_id": "IPz9tEQKz",
	"category": "Spices",
	"category_id": "rbuHbetmO",
	"name": "Cinnamon Sticks",
	"unit_id": "qkmUzGwng",
	"unit": "gm",
	"createdOn": {
		"$date": "2021-05-13T07:57:02Z"
	},
	"__v": 0,
	"stock": 0
}
{
	"_id": {
		"$oid": "609cdbe87df9360016fe04dd"
	},
	"ingredient_id": "mU1ZX2w56",
	"category": "Pouchong",
	"category_id": "vvecAwA8n",
	"name": "Concentrated Vinegar",
	"unit_id": "8-2Hs2tLw",
	"unit": "ml",
	"createdOn": {
		"$date": "2021-05-13T07:57:28Z"
	},
	"__v": 0,
	"stock": 0
}
{
	"_id": {
		"$oid": "609cdc187df9360016fe04de"
	},
	"ingredient_id": "wNGuvuQ8o",
	"category": "Vegetables",
	"category_id": "qrv8oa3rz",
	"name": "Coriander Leaf",
	"unit_id": "qkmUzGwng",
	"unit": "gm",
	"createdOn": {
		"$date": "2021-05-13T07:58:16Z"
	},
	"__v": 0,
	"stock": -25951
}
{
	"_id": {
		"$oid": "609cdc247df9360016fe04df"
	},
	"ingredient_id": "4q_usgkdZ",
	"category": "Vegetables",
	"category_id": "qrv8oa3rz",
	"name": "Corn",
	"unit_id": "qkmUzGwng",
	"unit": "gm",
	"createdOn": {
		"$date": "2021-05-13T07:58:28Z"
	},
	"__v": 0,
	"stock": 0
}
{
	"_id": {
		"$oid": "609cdc437df9360016fe04e0"
	},
	"ingredient_id": "v44fEANyr",
	"category": "Grocery",
	"category_id": "n3YT3gSBz",
	"name": "Cornflour",
	"unit_id": "qkmUzGwng",
	"unit": "gm",
	"createdOn": {
		"$date": "2021-05-13T07:58:59Z"
	},
	"__v": 0,
	"stock": -19700
}
{
	"_id": {
		"$oid": "609cdc5d7df9360016fe04e1"
	},
	"ingredient_id": "fNTacKFE5",
	"category": "Pouchong",
	"category_id": "vvecAwA8n",
	"name": "Cream of Sweet Corn",
	"unit_id": "qkmUzGwng",
	"unit": "gm",
	"createdOn": {
		"$date": "2021-05-13T07:59:24Z"
	},
	"__v": 0,
	"stock": 2250
}
{
	"_id": {
		"$oid": "609cdc6a7df9360016fe04e2"
	},
	"ingredient_id": "dP7oLdzS8",
	"category": "Vegetables",
	"category_id": "qrv8oa3rz",
	"name": "Cucumber",
	"unit_id": "qkmUzGwng",
	"unit": "gm",
	"createdOn": {
		"$date": "2021-05-13T07:59:38Z"
	},
	"__v": 0,
	"stock": 2350
}
{
	"_id": {
		"$oid": "609cdc787df9360016fe04e3"
	},
	"ingredient_id": "X_ow6LQn0",
	"category": "Dairy",
	"category_id": "qbZmJuFpV",
	"name": "Curd",
	"unit_id": "qkmUzGwng",
	"unit": "gm",
	"createdOn": {
		"$date": "2021-05-13T07:59:52Z"
	},
	"__v": 0,
	"stock": -66540
}
{
	"_id": {
		"$oid": "609cdc917df9360016fe04e4"
	},
	"ingredient_id": "MStAcDVd1",
	"category": "Pouchong",
	"category_id": "vvecAwA8n",
	"name": "Dark Soya Sauce",
	"unit_id": "8-2Hs2tLw",
	"unit": "ml",
	"createdOn": {
		"$date": "2021-05-13T08:00:17Z"
	},
	"__v": 0,
	"stock": -12270
}
{
	"_id": {
		"$oid": "609cdcb87df9360016fe04e5"
	},
	"ingredient_id": "nlnr0W9Bc",
	"category": "Spices",
	"category_id": "rbuHbetmO",
	"name": "Dhaniya Powder",
	"unit_id": "qkmUzGwng",
	"unit": "gm",
	"createdOn": {
		"$date": "2021-05-13T08:00:56Z"
	},
	"__v": 0,
	"stock": -19366
}
{
	"_id": {
		"$oid": "609cdccd7df9360016fe04e6"
	},
	"ingredient_id": "6m8WZ7Qgp",
	"category": "Spices",
	"category_id": "rbuHbetmO",
	"name": "Dry Red Chilli Powder",
	"unit_id": "qkmUzGwng",
	"unit": "gm",
	"createdOn": {
		"$date": "2021-05-13T08:01:17Z"
	},
	"__v": 0,
	"stock": -260
}
{
	"_id": {
		"$oid": "609cdce57df9360016fe04e7"
	},
	"ingredient_id": "louL9mbJ1",
	"category": "Spices",
	"category_id": "rbuHbetmO",
	"name": "Dry Red Chilli Whole",
	"unit_id": "qkmUzGwng",
	"unit": "gm",
	"createdOn": {
		"$date": "2021-05-13T08:01:41Z"
	},
	"__v": 0,
	"stock": -16
}
{
	"_id": {
		"$oid": "609cdd217df9360016fe04e8"
	},
	"ingredient_id": "YemihH8bl",
	"category": "Spices",
	"category_id": "rbuHbetmO",
	"name": "Elaichi",
	"unit_id": "qkmUzGwng",
	"unit": "gm",
	"createdOn": {
		"$date": "2021-05-13T08:02:41Z"
	},
	"__v": 0,
	"stock": 0
}
{
	"_id": {
		"$oid": "609cdd327df9360016fe04e9"
	},
	"ingredient_id": "UCPb7WJ09",
	"category": "Spices",
	"category_id": "rbuHbetmO",
	"name": "Elaichi Powder",
	"unit_id": "qkmUzGwng",
	"unit": "gm",
	"createdOn": {
		"$date": "2021-05-13T08:02:58Z"
	},
	"__v": 0,
	"stock": -7145
}
{
	"_id": {
		"$oid": "609cdd447df9360016fe04ea"
	},
	"ingredient_id": "N3b427Fn2",
	"category": "Grocery",
	"category_id": "n3YT3gSBz",
	"name": "Flour",
	"unit_id": "qkmUzGwng",
	"unit": "gm",
	"createdOn": {
		"$date": "2021-05-13T08:03:16Z"
	},
	"__v": 0,
	"stock": -1179600
}
{
	"_id": {
		"$oid": "609cdd607df9360016fe04eb"
	},
	"ingredient_id": "DpnO-HUgg",
	"category": "Dairy",
	"category_id": "qbZmJuFpV",
	"name": "Fresh Cream",
	"unit_id": "qkmUzGwng",
	"unit": "gm",
	"createdOn": {
		"$date": "2021-05-13T08:03:44Z"
	},
	"__v": 0,
	"stock": -42295
}
{
	"_id": {
		"$oid": "609cdd737df9360016fe04ec"
	},
	"ingredient_id": "XJWewxz-E",
	"category": "Spices",
	"category_id": "rbuHbetmO",
	"name": "Garam Masala",
	"unit_id": "qkmUzGwng",
	"unit": "gm",
	"createdOn": {
		"$date": "2021-05-13T08:04:03Z"
	},
	"__v": 0,
	"stock": -655
}
{
	"_id": {
		"$oid": "609cde2b7df9360016fe04ed"
	},
	"ingredient_id": "EpLFKm0xm",
	"category": "Vegetables",
	"category_id": "qrv8oa3rz",
	"name": "Garlic Leaf",
	"unit_id": "qkmUzGwng",
	"unit": "gm",
	"createdOn": {
		"$date": "2021-05-13T08:07:07Z"
	},
	"__v": 0,
	"stock": -420
}
{
	"_id": {
		"$oid": "609cde427df9360016fe04ee"
	},
	"ingredient_id": "fJ6dhFSyC",
	"category": "Vegetables",
	"category_id": "qrv8oa3rz",
	"name": "Garlic Pealed",
	"unit_id": "qkmUzGwng",
	"unit": "gm",
	"createdOn": {
		"$date": "2021-05-13T08:07:30Z"
	},
	"__v": 0,
	"stock": -30988
}
{
	"_id": {
		"$oid": "609cde627df9360016fe04ef"
	},
	"ingredient_id": "KxWPhBXEl",
	"category": "Spices",
	"category_id": "rbuHbetmO",
	"name": "Garlic Sauce",
	"unit_id": "qkmUzGwng",
	"unit": "gm",
	"createdOn": {
		"$date": "2021-05-13T08:08:02Z"
	},
	"__v": 0,
	"stock": -12
}
{
	"_id": {
		"$oid": "609cde767df9360016fe04f0"
	},
	"ingredient_id": "inGwOdBGs",
	"category": "Vegetables",
	"category_id": "qrv8oa3rz",
	"name": "Garlic Whole",
	"unit_id": "qkmUzGwng",
	"unit": "gm",
	"createdOn": {
		"$date": "2021-05-13T08:08:22Z"
	},
	"__v": 0,
	"stock": -4550
}
{
	"_id": {
		"$oid": "609cde867df9360016fe04f1"
	},
	"ingredient_id": "64DGDVrW8",
	"category": "Others",
	"category_id": "HuA2RO0kJ",
	"name": "GAS",
	"unit_id": "qkmUzGwng",
	"unit": "gm",
	"createdOn": {
		"$date": "2021-05-13T08:08:38Z"
	},
	"__v": 0,
	"stock": 0
}
{
	"_id": {
		"$oid": "609cdeaf7df9360016fe04f2"
	},
	"ingredient_id": "p27viiAHM",
	"category": "Pouchong",
	"category_id": "vvecAwA8n",
	"name": "Green Food Colour",
	"unit_id": "qkmUzGwng",
	"unit": "gm",
	"createdOn": {
		"$date": "2021-05-13T08:09:19Z"
	},
	"__v": 0,
	"stock": 0
}
{
	"_id": {
		"$oid": "609cdec17df9360016fe04f3"
	},
	"ingredient_id": "B2l0fpQS_",
	"category": "Grocery",
	"category_id": "n3YT3gSBz",
	"name": "Ghee",
	"unit_id": "qkmUzGwng",
	"unit": "gm",
	"createdOn": {
		"$date": "2021-05-13T08:09:37Z"
	},
	"__v": 0,
	"stock": -4460
}
{
	"_id": {
		"$oid": "609cded57df9360016fe04f4"
	},
	"ingredient_id": "oL-X3c4_B",
	"category": "Vegetables",
	"category_id": "qrv8oa3rz",
	"name": "Ginger",
	"unit_id": "qkmUzGwng",
	"unit": "gm",
	"createdOn": {
		"$date": "2021-05-13T08:09:57Z"
	},
	"__v": 0,
	"stock": -23638
}
{
	"_id": {
		"$oid": "609cdeea7df9360016fe04f5"
	},
	"ingredient_id": "Y4vND3cMv",
	"category": "Vegetables",
	"category_id": "qrv8oa3rz",
	"name": "Ginger Leaf",
	"unit_id": "qkmUzGwng",
	"unit": "gm",
	"createdOn": {
		"$date": "2021-05-13T08:10:18Z"
	},
	"__v": 0,
	"stock": -1580
}
{
	"_id": {
		"$oid": "609cdefd7df9360016fe04f6"
	},
	"ingredient_id": "vR5XbXc5r",
	"category": "Vegetables",
	"category_id": "qrv8oa3rz",
	"name": "Green Capsicum",
	"unit_id": "qkmUzGwng",
	"unit": "gm",
	"createdOn": {
		"$date": "2021-05-13T08:10:37Z"
	},
	"__v": 0,
	"stock": -19760
}
{
	"_id": {
		"$oid": "609cdf0c7df9360016fe04f7"
	},
	"ingredient_id": "58F_a9xSa",
	"category": "Vegetables",
	"category_id": "qrv8oa3rz",
	"name": "Green Chilli",
	"unit_id": "qkmUzGwng",
	"unit": "gm",
	"createdOn": {
		"$date": "2021-05-13T08:10:52Z"
	},
	"__v": 0,
	"stock": -24209
}
{
	"_id": {
		"$oid": "609cdf237df9360016fe04f8"
	},
	"ingredient_id": "Se_XccZ8X",
	"category": "Pouchong",
	"category_id": "vvecAwA8n",
	"name": "Green Chilli Sauce",
	"unit_id": "8-2Hs2tLw",
	"unit": "ml",
	"createdOn": {
		"$date": "2021-05-13T08:11:15Z"
	},
	"__v": 0,
	"stock": -27349
}
{
	"_id": {
		"$oid": "609cdf867df9360016fe04f9"
	},
	"ingredient_id": "kxBbLaWpX",
	"category": "Grocery",
	"category_id": "n3YT3gSBz",
	"name": "Haldi Powder",
	"unit_id": "qkmUzGwng",
	"unit": "gm",
	"createdOn": {
		"$date": "2021-05-13T08:12:54Z"
	},
	"__v": 0,
	"stock": -6830
}
{
	"_id": {
		"$oid": "609cdfb57df9360016fe04fa"
	},
	"ingredient_id": "mU96tfrg-",
	"category": "Pouchong",
	"category_id": "vvecAwA8n",
	"name": "Hot Garlic Sauce",
	"unit_id": "8-2Hs2tLw",
	"unit": "ml",
	"createdOn": {
		"$date": "2021-05-13T08:13:41Z"
	},
	"__v": 0,
	"stock": -34705
}
{
	"_id": {
		"$oid": "609cdfd67df9360016fe04fb"
	},
	"ingredient_id": "3WT_N-Q1B",
	"category": "Fish",
	"category_id": "nwfim3VxF",
	"name": "Indian Basa Fish",
	"unit_id": "qkmUzGwng",
	"unit": "gm",
	"createdOn": {
		"$date": "2021-05-13T08:14:14Z"
	},
	"__v": 0,
	"stock": 0
}
{
	"_id": {
		"$oid": "609ce0087df9360016fe04fc"
	},
	"ingredient_id": "DiKOHC0GS",
	"category": "Poultry",
	"category_id": "ym2_N2UNX",
	"name": "Indian Gravy Chicken",
	"unit_id": "qkmUzGwng",
	"unit": "gm",
	"createdOn": {
		"$date": "2021-05-13T08:15:04Z"
	},
	"__v": 0,
	"stock": -120800
}
{
	"_id": {
		"$oid": "609ce0187df9360016fe04fd"
	},
	"ingredient_id": "5rZK8f8Z7",
	"category": "Spices",
	"category_id": "rbuHbetmO",
	"name": "Jayfal",
	"unit_id": "qkmUzGwng",
	"unit": "gm",
	"createdOn": {
		"$date": "2021-05-13T08:15:20Z"
	},
	"__v": 0,
	"stock": 0
}
{
	"_id": {
		"$oid": "609ce02a7df9360016fe04fe"
	},
	"ingredient_id": "1fcTO2zlz",
	"category": "Spices",
	"category_id": "rbuHbetmO",
	"name": "Jayitri",
	"unit_id": "qkmUzGwng",
	"unit": "gm",
	"createdOn": {
		"$date": "2021-05-13T08:15:38Z"
	},
	"__v": 0,
	"stock": 0
}
{
	"_id": {
		"$oid": "609ce03b7df9360016fe04ff"
	},
	"ingredient_id": "p0f5stZ_5",
	"category": "Spices",
	"category_id": "rbuHbetmO",
	"name": "Jeera Powder",
	"unit_id": "qkmUzGwng",
	"unit": "gm",
	"createdOn": {
		"$date": "2021-05-13T08:15:55Z"
	},
	"__v": 0,
	"stock": -19735
}
{
	"_id": {
		"$oid": "609ce04f7df9360016fe0500"
	},
	"ingredient_id": "D1rLv3e4G",
	"category": "Grocery",
	"category_id": "n3YT3gSBz",
	"name": "Kabli Chana",
	"unit_id": "qkmUzGwng",
	"unit": "gm",
	"createdOn": {
		"$date": "2021-05-13T08:16:15Z"
	},
	"__v": 0,
	"stock": -2600
}
{
	"_id": {
		"$oid": "609ce05f7df9360016fe0501"
	},
	"ingredient_id": "_4obElvoA",
	"category": "Spices",
	"category_id": "rbuHbetmO",
	"name": "Kaju",
	"unit_id": "qkmUzGwng",
	"unit": "gm",
	"createdOn": {
		"$date": "2021-05-13T08:16:31Z"
	},
	"__v": 0,
	"stock": -4515
}
{
	"_id": {
		"$oid": "609ce0717df9360016fe0502"
	},
	"ingredient_id": "rtS246rAm",
	"category": "Spices",
	"category_id": "rbuHbetmO",
	"name": "Kashmiri Mirch Powder",
	"unit_id": "qkmUzGwng",
	"unit": "gm",
	"createdOn": {
		"$date": "2021-05-13T08:16:49Z"
	},
	"__v": 0,
	"stock": -7560
}
{
	"_id": {
		"$oid": "609ce0847df9360016fe0503"
	},
	"ingredient_id": "TjJTky9JM",
	"category": "Spices",
	"category_id": "rbuHbetmO",
	"name": "Kasturi Methi",
	"unit_id": "qkmUzGwng",
	"unit": "gm",
	"createdOn": {
		"$date": "2021-05-13T08:17:08Z"
	},
	"__v": 0,
	"stock": -7183
}
{
	"_id": {
		"$oid": "609ce0967df9360016fe0504"
	},
	"ingredient_id": "Qa9SQAb4B",
	"category": "Pouchong",
	"category_id": "vvecAwA8n",
	"name": "Kasundi",
	"unit_id": "8-2Hs2tLw",
	"unit": "ml",
	"createdOn": {
		"$date": "2021-05-13T08:17:26Z"
	},
	"__v": 0,
	"stock": 0
}
{
	"_id": {
		"$oid": "609ce0b67df9360016fe0505"
	},
	"ingredient_id": "1X83Vsoj1",
	"category": "Spices",
	"category_id": "rbuHbetmO",
	"name": "Kishmish(Rasins)",
	"unit_id": "qkmUzGwng",
	"unit": "gm",
	"createdOn": {
		"$date": "2021-05-13T08:17:58Z"
	},
	"__v": 0,
	"stock": -565
}
{
	"_id": {
		"$oid": "609ce0cc7df9360016fe0506"
	},
	"ingredient_id": "Ejbaty5U4",
	"category": "Grocery",
	"category_id": "n3YT3gSBz",
	"name": "Kitchen King",
	"unit_id": "qkmUzGwng",
	"unit": "gm",
	"createdOn": {
		"$date": "2021-05-13T08:18:20Z"
	},
	"__v": 0,
	"stock": -3940
}
{
	"_id": {
		"$oid": "609ce0db7df9360016fe0507"
	},
	"ingredient_id": "KKwVnQt1G",
	"category": "Vegetables",
	"category_id": "qrv8oa3rz",
	"name": "Lemon",
	"unit_id": "-cf60bJYu",
	"unit": "pc",
	"createdOn": {
		"$date": "2021-05-13T08:18:35Z"
	},
	"__v": 0,
	"stock": -2199.5
}
{
	"_id": {
		"$oid": "609ce0f27df9360016fe0508"
	},
	"ingredient_id": "MO-dTSEcX",
	"category": "Vegetables",
	"category_id": "qrv8oa3rz",
	"name": "Lemon Leaf",
	"unit_id": "qkmUzGwng",
	"unit": "gm",
	"createdOn": {
		"$date": "2021-05-13T08:18:58Z"
	},
	"__v": 0,
	"stock": 0
}
{
	"_id": {
		"$oid": "609ce1047df9360016fe0509"
	},
	"ingredient_id": "YHgbbPSHi",
	"category": "Spices",
	"category_id": "rbuHbetmO",
	"name": "Methi",
	"unit_id": "qkmUzGwng",
	"unit": "gm",
	"createdOn": {
		"$date": "2021-05-13T08:19:16Z"
	},
	"__v": 0,
	"stock": -1550
}
{
	"_id": {
		"$oid": "609ce1207df9360016fe050a"
	},
	"ingredient_id": "BFqGYJrdJ",
	"category": "Dairy",
	"category_id": "qbZmJuFpV",
	"name": "Milk",
	"unit_id": "8-2Hs2tLw",
	"unit": "ml",
	"createdOn": {
		"$date": "2021-05-13T08:19:44Z"
	},
	"__v": 0,
	"stock": -29468.799999999945
}
{
	"_id": {
		"$oid": "609ce14c7df9360016fe050b"
	},
	"ingredient_id": "CzMBSbL-1",
	"category": "Prawn",
	"category_id": "YaHAkjayD",
	"name": "Minced Prawn",
	"unit_id": "qkmUzGwng",
	"unit": "gm",
	"createdOn": {
		"$date": "2021-05-13T08:20:28Z"
	},
	"__v": 0,
	"stock": -105
}
{
	"_id": {
		"$oid": "609ce15e7df9360016fe050c"
	},
	"ingredient_id": "2a6vjHsv4",
	"category": "Grocery",
	"category_id": "n3YT3gSBz",
	"name": "Moong Dal",
	"unit_id": "qkmUzGwng",
	"unit": "gm",
	"createdOn": {
		"$date": "2021-05-13T08:20:46Z"
	},
	"__v": 0,
	"stock": -210
}
{
	"_id": {
		"$oid": "609ce1817df9360016fe050d"
	},
	"ingredient_id": "n7wTe9bPy",
	"category": "Pouchong",
	"category_id": "vvecAwA8n",
	"name": "Mushroom",
	"unit_id": "qkmUzGwng",
	"unit": "gm",
	"createdOn": {
		"$date": "2021-05-13T08:21:21Z"
	},
	"__v": 0,
	"stock": -1515
}
{
	"_id": {
		"$oid": "609ce1957df9360016fe050e"
	},
	"ingredient_id": "zyS-wRqDU",
	"category": "Grocery",
	"category_id": "n3YT3gSBz",
	"name": "Mustard Oil",
	"unit_id": "8-2Hs2tLw",
	"unit": "ml",
	"createdOn": {
		"$date": "2021-05-13T08:21:41Z"
	},
	"__v": 0,
	"stock": -97880
}
{
	"_id": {
		"$oid": "609ce1a87df9360016fe050f"
	},
	"ingredient_id": "bmag2vPua",
	"category": "Grocery",
	"category_id": "n3YT3gSBz",
	"name": "Masur Dal",
	"unit_id": "qkmUzGwng",
	"unit": "gm",
	"createdOn": {
		"$date": "2021-05-13T08:22:00Z"
	},
	"__v": 0,
	"stock": -470
}
{
	"_id": {
		"$oid": "609ce1c17df9360016fe0510"
	},
	"ingredient_id": "n8mLDBP57",
	"category": "Mutton",
	"category_id": "lT0LWJtRc",
	"name": "Mutton Boneless",
	"unit_id": "qkmUzGwng",
	"unit": "gm",
	"createdOn": {
		"$date": "2021-05-13T08:22:25Z"
	},
	"__v": 0,
	"stock": 700
}
{
	"_id": {
		"$oid": "609ce22f7df9360016fe0511"
	},
	"ingredient_id": "7UWbVLHFH",
	"category": "Mutton",
	"category_id": "lT0LWJtRc",
	"name": "Mutton Minced",
	"unit_id": "qkmUzGwng",
	"unit": "gm",
	"createdOn": {
		"$date": "2021-05-13T08:24:15Z"
	},
	"__v": 0,
	"stock": -200
}
{
	"_id": {
		"$oid": "609ce2507df9360016fe0512"
	},
	"ingredient_id": "zIJEerZUv",
	"category": "Pouchong",
	"category_id": "vvecAwA8n",
	"name": "Noodles",
	"unit_id": "qkmUzGwng",
	"unit": "gm",
	"createdOn": {
		"$date": "2021-05-13T08:24:48Z"
	},
	"__v": 0,
	"stock": -25
}
{
	"_id": {
		"$oid": "609ce2607df9360016fe0513"
	},
	"ingredient_id": "J-cTFlJ-5",
	"category": "Vegetables",
	"category_id": "qrv8oa3rz",
	"name": "Onion",
	"unit_id": "qkmUzGwng",
	"unit": "gm",
	"createdOn": {
		"$date": "2021-05-13T08:25:04Z"
	},
	"__v": 0,
	"stock": -337780
}
{
	"_id": {
		"$oid": "609ce2bf7df9360016fe0514"
	},
	"ingredient_id": "1hKu6rAcS",
	"category": "Vegetables",
	"category_id": "qrv8oa3rz",
	"name": "Onion Leaf",
	"unit_id": "qkmUzGwng",
	"unit": "gm",
	"createdOn": {
		"$date": "2021-05-13T08:26:39Z"
	},
	"__v": 0,
	"stock": 0
}
{
	"_id": {
		"$oid": "609ce2ea7df9360016fe0515"
	},
	"ingredient_id": "j5uCho4nr",
	"category": "Pouchong",
	"category_id": "vvecAwA8n",
	"name": "Oyester Sauce",
	"unit_id": "8-2Hs2tLw",
	"unit": "ml",
	"createdOn": {
		"$date": "2021-05-13T08:27:22Z"
	},
	"__v": 0,
	"stock": 0
}
{
	"_id": {
		"$oid": "609ce35a7df9360016fe0516"
	},
	"ingredient_id": "6jZRlZcsM",
	"category": "Vegetables",
	"category_id": "qrv8oa3rz",
	"name": "Pakchoi",
	"unit_id": "qkmUzGwng",
	"unit": "gm",
	"createdOn": {
		"$date": "2021-05-13T08:29:14Z"
	},
	"__v": 0,
	"stock": 0
}
{
	"_id": {
		"$oid": "609ce3737df9360016fe0517"
	},
	"ingredient_id": "7ndzEvlTl",
	"category": "Vegetables",
	"category_id": "qrv8oa3rz",
	"name": "Pakchoi",
	"unit_id": "qkmUzGwng",
	"unit": "gm",
	"createdOn": {
		"$date": "2021-05-13T08:29:39Z"
	},
	"__v": 0,
	"stock": 0
}
{
	"_id": {
		"$oid": "609ce3887df9360016fe0518"
	},
	"ingredient_id": "2EnCQmyqq",
	"category": "Dairy",
	"category_id": "qbZmJuFpV",
	"name": "Paneer",
	"unit_id": "qkmUzGwng",
	"unit": "gm",
	"createdOn": {
		"$date": "2021-05-13T08:30:00Z"
	},
	"__v": 0,
	"stock": -157115
}
{
	"_id": {
		"$oid": "609ce39b7df9360016fe0519"
	},
	"ingredient_id": "1h4Z4wlMD",
	"category": "Vegetables",
	"category_id": "qrv8oa3rz",
	"name": "Peas",
	"unit_id": "qkmUzGwng",
	"unit": "gm",
	"createdOn": {
		"$date": "2021-05-13T08:30:19Z"
	},
	"__v": 0,
	"stock": -14150
}
{
	"_id": {
		"$oid": "609ce3b87df9360016fe051a"
	},
	"ingredient_id": "_UmH9rXTn",
	"category": "Pouchong",
	"category_id": "vvecAwA8n",
	"name": "Pineapple Tin",
	"unit_id": "qkmUzGwng",
	"unit": "gm",
	"createdOn": {
		"$date": "2021-05-13T08:30:48Z"
	},
	"__v": 0,
	"stock": 0
}
{
	"_id": {
		"$oid": "609ce3cc7df9360016fe051b"
	},
	"ingredient_id": "Z4zQnlBdy",
	"category": "Vegetables",
	"category_id": "qrv8oa3rz",
	"name": "Pudina Leaf",
	"unit_id": "qkmUzGwng",
	"unit": "gm",
	"createdOn": {
		"$date": "2021-05-13T08:31:08Z"
	},
	"__v": 0,
	"stock": 250
}
{
	"_id": {
		"$oid": "609ce3dd7df9360016fe051c"
	},
	"ingredient_id": "A33XMtgVa",
	"category": "Grocery",
	"category_id": "n3YT3gSBz",
	"name": "Rajma",
	"unit_id": "qkmUzGwng",
	"unit": "gm",
	"createdOn": {
		"$date": "2021-05-13T08:31:25Z"
	},
	"__v": 0,
	"stock": -7800
}
{
	"_id": {
		"$oid": "609ce3ed7df9360016fe051d"
	},
	"ingredient_id": "2qR0-P-z6",
	"category": "Vegetables",
	"category_id": "qrv8oa3rz",
	"name": "Red Capsicum",
	"unit_id": "qkmUzGwng",
	"unit": "gm",
	"createdOn": {
		"$date": "2021-05-13T08:31:41Z"
	},
	"__v": 0,
	"stock": -5500
}
{
	"_id": {
		"$oid": "609ce4057df9360016fe051e"
	},
	"ingredient_id": "u9S7nMJdF",
	"category": "Pouchong",
	"category_id": "vvecAwA8n",
	"name": "Red Chilli Sauce",
	"unit_id": "8-2Hs2tLw",
	"unit": "ml",
	"createdOn": {
		"$date": "2021-05-13T08:32:05Z"
	},
	"__v": 0,
	"stock": 0
}
{
	"_id": {
		"$oid": "609ce4217df9360016fe051f"
	},
	"ingredient_id": "CaMLz6Ad0",
	"category": "Pouchong",
	"category_id": "vvecAwA8n",
	"name": "Red Food Colour",
	"unit_id": "qkmUzGwng",
	"unit": "gm",
	"createdOn": {
		"$date": "2021-05-13T08:32:33Z"
	},
	"__v": 0,
	"stock": -3635
}
{
	"_id": {
		"$oid": "609ce4377df9360016fe0520"
	},
	"ingredient_id": "CVkJmXAoa",
	"category": "Pouchong",
	"category_id": "vvecAwA8n",
	"name": "Red Yellow Food Colour",
	"unit_id": "qkmUzGwng",
	"unit": "gm",
	"createdOn": {
		"$date": "2021-05-13T08:32:55Z"
	},
	"__v": 0,
	"stock": -150
}
{
	"_id": {
		"$oid": "609ce4437df9360016fe0521"
	},
	"ingredient_id": "IwXWNHobZ",
	"category": "Grocery",
	"category_id": "n3YT3gSBz",
	"name": "Rice",
	"unit_id": "qkmUzGwng",
	"unit": "gm",
	"createdOn": {
		"$date": "2021-05-13T08:33:07Z"
	},
	"__v": 0,
	"stock": -9600
}
{
	"_id": {
		"$oid": "609ce45b7df9360016fe0522"
	},
	"ingredient_id": "4SPeg5BMf",
	"category": "Grocery",
	"category_id": "n3YT3gSBz",
	"name": "Rice Bran Oil",
	"unit_id": "8-2Hs2tLw",
	"unit": "ml",
	"createdOn": {
		"$date": "2021-05-13T08:33:31Z"
	},
	"__v": 0,
	"stock": 10920
}
{
	"_id": {
		"$oid": "609ce4697df9360016fe0523"
	},
	"ingredient_id": "zMYxAvJrW",
	"category": "Pouchong",
	"category_id": "vvecAwA8n",
	"name": "Rice Wine",
	"unit_id": "8-2Hs2tLw",
	"unit": "ml",
	"createdOn": {
		"$date": "2021-05-13T08:33:45Z"
	},
	"__v": 0,
	"stock": -5220
}
{
	"_id": {
		"$oid": "609ce4797df9360016fe0524"
	},
	"ingredient_id": "7p8q0YCf8",
	"category": "Grocery",
	"category_id": "n3YT3gSBz",
	"name": "Salt",
	"unit_id": "qkmUzGwng",
	"unit": "gm",
	"createdOn": {
		"$date": "2021-05-13T08:34:01Z"
	},
	"__v": 0,
	"stock": -66689.75000000004
}
{
	"_id": {
		"$oid": "609ce4917df9360016fe0525"
	},
	"ingredient_id": "FT3ExzT0N",
	"category": "Pouchong",
	"category_id": "vvecAwA8n",
	"name": "Schezwan Sauce",
	"unit_id": "qkmUzGwng",
	"unit": "gm",
	"createdOn": {
		"$date": "2021-05-13T08:34:25Z"
	},
	"__v": 0,
	"stock": 0
}
{
	"_id": {
		"$oid": "609ce4ad7df9360016fe0526"
	},
	"ingredient_id": "a1B0-BOdt",
	"category": "Pouchong",
	"category_id": "vvecAwA8n",
	"name": "Sesame Oil",
	"unit_id": "8-2Hs2tLw",
	"unit": "ml",
	"createdOn": {
		"$date": "2021-05-13T08:34:53Z"
	},
	"__v": 0,
	"stock": -10230
}
{
	"_id": {
		"$oid": "609ce4bf7df9360016fe0527"
	},
	"ingredient_id": "uIVMlev-x",
	"category": "Spices",
	"category_id": "rbuHbetmO",
	"name": "Shah Jeera",
	"unit_id": "qkmUzGwng",
	"unit": "gm",
	"createdOn": {
		"$date": "2021-05-13T08:35:11Z"
	},
	"__v": 0,
	"stock": -1795
}
{
	"_id": {
		"$oid": "609ce4e57df9360016fe0528"
	},
	"ingredient_id": "FqLuKrRP-",
	"category": "Prawn",
	"category_id": "YaHAkjayD",
	"name": "Shrimp",
	"unit_id": "qkmUzGwng",
	"unit": "gm",
	"createdOn": {
		"$date": "2021-05-13T08:35:49Z"
	},
	"__v": 0,
	"stock": 4250
}
{
	"_id": {
		"$oid": "609ce4ff7df9360016fe0529"
	},
	"ingredient_id": "KLOQi93fB",
	"category": "Pouchong",
	"category_id": "vvecAwA8n",
	"name": "Singapore Sauce",
	"unit_id": "8-2Hs2tLw",
	"unit": "ml",
	"createdOn": {
		"$date": "2021-05-13T08:36:15Z"
	},
	"__v": 0,
	"stock": 0
}
{
	"_id": {
		"$oid": "609ce50e7df9360016fe052a"
	},
	"ingredient_id": "y23mUVH-y",
	"category": "Pouchong",
	"category_id": "vvecAwA8n",
	"name": "Soya Sauce",
	"unit_id": "8-2Hs2tLw",
	"unit": "ml",
	"createdOn": {
		"$date": "2021-05-13T08:36:30Z"
	},
	"__v": 0,
	"stock": -80
}
{
	"_id": {
		"$oid": "609ce5237df9360016fe052b"
	},
	"ingredient_id": "lM8dPPJM8",
	"category": "Grocery",
	"category_id": "n3YT3gSBz",
	"name": "Soyabean Oil",
	"unit_id": "8-2Hs2tLw",
	"unit": "ml",
	"createdOn": {
		"$date": "2021-05-13T08:36:51Z"
	},
	"__v": 0,
	"stock": -200004
}
{
	"_id": {
		"$oid": "609ce53d7df9360016fe052c"
	},
	"ingredient_id": "slY5XjEjt",
	"category": "Vegetables",
	"category_id": "qrv8oa3rz",
	"name": "Spring Onions",
	"unit_id": "qkmUzGwng",
	"unit": "gm",
	"createdOn": {
		"$date": "2021-05-13T08:37:17Z"
	},
	"__v": 0,
	"stock": -43790
}
{
	"_id": {
		"$oid": "609ce54d7df9360016fe052d"
	},
	"ingredient_id": "-Kxk-WB7d",
	"category": "Spices",
	"category_id": "rbuHbetmO",
	"name": "Star Anise",
	"unit_id": "qkmUzGwng",
	"unit": "gm",
	"createdOn": {
		"$date": "2021-05-13T08:37:33Z"
	},
	"__v": 0,
	"stock": 1000
}
{
	"_id": {
		"$oid": "609ce5607df9360016fe052e"
	},
	"ingredient_id": "lmMnwTo1f",
	"category": "Grocery",
	"category_id": "n3YT3gSBz",
	"name": "Sugar",
	"unit_id": "qkmUzGwng",
	"unit": "gm",
	"createdOn": {
		"$date": "2021-05-13T08:37:52Z"
	},
	"__v": 0,
	"stock": -71918
}
{
	"_id": {
		"$oid": "609ce5867df9360016fe052f"
	},
	"ingredient_id": "f2bSgsBud",
	"category": "Spices",
	"category_id": "rbuHbetmO",
	"name": "Tandoori Chicken Masala",
	"unit_id": "qkmUzGwng",
	"unit": "gm",
	"createdOn": {
		"$date": "2021-05-13T08:38:30Z"
	},
	"__v": 0,
	"stock": -4455
}
{
	"_id": {
		"$oid": "609ce5d27df9360016fe0530"
	},
	"ingredient_id": "9B1YH0pVG",
	"category": "Spices",
	"category_id": "rbuHbetmO",
	"name": "Tandoori Masala",
	"unit_id": "qkmUzGwng",
	"unit": "gm",
	"createdOn": {
		"$date": "2021-05-13T08:39:46Z"
	},
	"__v": 0,
	"stock": -4730
}
{
	"_id": {
		"$oid": "609ce5eb7df9360016fe0531"
	},
	"ingredient_id": "vEzrNq7YK",
	"category": "Spices",
	"category_id": "rbuHbetmO",
	"name": "Tarka Masala",
	"unit_id": "qkmUzGwng",
	"unit": "gm",
	"createdOn": {
		"$date": "2021-05-13T08:40:11Z"
	},
	"__v": 0,
	"stock": -2840
}
{
	"_id": {
		"$oid": "609ce6037df9360016fe0532"
	},
	"ingredient_id": "jmIUzMcuZ",
	"category": "Vegetables",
	"category_id": "qrv8oa3rz",
	"name": "Thai Ginger",
	"unit_id": "qkmUzGwng",
	"unit": "gm",
	"createdOn": {
		"$date": "2021-05-13T08:40:35Z"
	},
	"__v": 0,
	"stock": 0
}
{
	"_id": {
		"$oid": "609ce6217df9360016fe0533"
	},
	"ingredient_id": "4Xel4HTPs",
	"category": "Pouchong",
	"category_id": "vvecAwA8n",
	"name": "Thai Sweet Chilli Sauce",
	"unit_id": "8-2Hs2tLw",
	"unit": "ml",
	"createdOn": {
		"$date": "2021-05-13T08:41:05Z"
	},
	"__v": 0,
	"stock": 0
}
{
	"_id": {
		"$oid": "609ce6387df9360016fe0534"
	},
	"ingredient_id": "pCs61kRfM",
	"category": "Prawn",
	"category_id": "YaHAkjayD",
	"name": "Tiger Prawn",
	"unit_id": "qkmUzGwng",
	"unit": "gm",
	"createdOn": {
		"$date": "2021-05-13T08:41:28Z"
	},
	"__v": 0,
	"stock": 0
}
{
	"_id": {
		"$oid": "609ce67b7df9360016fe0535"
	},
	"ingredient_id": "Zfu8I7oJ2",
	"category": "Vegetables",
	"category_id": "qrv8oa3rz",
	"name": "Tomato",
	"unit_id": "qkmUzGwng",
	"unit": "gm",
	"createdOn": {
		"$date": "2021-05-13T08:42:35Z"
	},
	"__v": 0,
	"stock": -35830
}
{
	"_id": {
		"$oid": "609ce6907df9360016fe0536"
	},
	"ingredient_id": "_pxFWQQBl",
	"category": "Pouchong",
	"category_id": "vvecAwA8n",
	"name": "Tomato Puree",
	"unit_id": "qkmUzGwng",
	"unit": "gm",
	"createdOn": {
		"$date": "2021-05-13T08:42:56Z"
	},
	"__v": 0,
	"stock": -290
}
{
	"_id": {
		"$oid": "609ce6a97df9360016fe0537"
	},
	"ingredient_id": "KK0I7bQ9c",
	"category": "Pouchong",
	"category_id": "vvecAwA8n",
	"name": "Tomato Sauce",
	"unit_id": "qkmUzGwng",
	"unit": "gm",
	"createdOn": {
		"$date": "2021-05-13T08:43:21Z"
	},
	"__v": 0,
	"stock": -714
}
{
	"_id": {
		"$oid": "609ce6c17df9360016fe0538"
	},
	"ingredient_id": "OnJs3KNQo",
	"category": "Vegetables",
	"category_id": "qrv8oa3rz",
	"name": "Turmeric",
	"unit_id": "qkmUzGwng",
	"unit": "gm",
	"createdOn": {
		"$date": "2021-05-13T08:43:45Z"
	},
	"__v": 0,
	"stock": -4700
}
{
	"_id": {
		"$oid": "609ce6ee7df9360016fe0539"
	},
	"ingredient_id": "oDwTcmrCE",
	"category": "Spices",
	"category_id": "rbuHbetmO",
	"name": "Turmeric Dried Whole",
	"unit_id": "qkmUzGwng",
	"unit": "gm",
	"createdOn": {
		"$date": "2021-05-13T08:44:30Z"
	},
	"__v": 0,
	"stock": 0
}
{
	"_id": {
		"$oid": "609ce7237df9360016fe053a"
	},
	"ingredient_id": "_BaJMcSHk",
	"category": "Spices",
	"category_id": "rbuHbetmO",
	"name": "Turmeric Powder",
	"unit_id": "qkmUzGwng",
	"unit": "gm",
	"createdOn": {
		"$date": "2021-05-13T08:45:23Z"
	},
	"__v": 0,
	"stock": -40
}
{
	"_id": {
		"$oid": "609ce7317df9360016fe053b"
	},
	"ingredient_id": "80-rhqvrp",
	"category": "Pouchong",
	"category_id": "vvecAwA8n",
	"name": "Vinegar",
	"unit_id": "8-2Hs2tLw",
	"unit": "ml",
	"createdOn": {
		"$date": "2021-05-13T08:45:37Z"
	},
	"__v": 0,
	"stock": 1035
}
{
	"_id": {
		"$oid": "609ce7437df9360016fe053c"
	},
	"ingredient_id": "yJhP2HHFW",
	"category": "Spices",
	"category_id": "rbuHbetmO",
	"name": "White Pepper",
	"unit_id": "qkmUzGwng",
	"unit": "gm",
	"createdOn": {
		"$date": "2021-05-13T08:45:55Z"
	},
	"__v": 0,
	"stock": -12300
}
{
	"_id": {
		"$oid": "609ce7567df9360016fe053d"
	},
	"ingredient_id": "0QQeRBCNX",
	"category": "Spices",
	"category_id": "rbuHbetmO",
	"name": "White Till",
	"unit_id": "qkmUzGwng",
	"unit": "gm",
	"createdOn": {
		"$date": "2021-05-13T08:46:14Z"
	},
	"__v": 0,
	"stock": -29910
}
{
	"_id": {
		"$oid": "609ce77b7df9360016fe053e"
	},
	"ingredient_id": "l_3mJMgzO",
	"category": "Poultry",
	"category_id": "ym2_N2UNX",
	"name": "Whole Tender Chicken",
	"unit_id": "qkmUzGwng",
	"unit": "gm",
	"createdOn": {
		"$date": "2021-05-13T08:46:51Z"
	},
	"__v": 0,
	"stock": 0
}
{
	"_id": {
		"$oid": "609ce7917df9360016fe053f"
	},
	"ingredient_id": "mpE1rGVJy",
	"category": "Vegetables",
	"category_id": "qrv8oa3rz",
	"name": "Yellow Capsicum",
	"unit_id": "qkmUzGwng",
	"unit": "gm",
	"createdOn": {
		"$date": "2021-05-13T08:47:13Z"
	},
	"__v": 0,
	"stock": -5770
}
{
	"_id": {
		"$oid": "60a49d00e156d10016852196"
	},
	"ingredient_id": "jAH6PLtAz",
	"category": "test",
	"category_id": "VCf8Cgt0y",
	"name": "Test21",
	"unit_id": "ZaERVhvoc",
	"unit": "t22",
	"createdOn": {
		"$date": "2021-05-19T05:07:11Z"
	},
	"__v": 0,
	"stock": 0
}
{
	"_id": {
		"$oid": "60c625277ab9b90016e52dee"
	},
	"ingredient_id": "MgWjx04Ev",
	"category": "Grocery",
	"category_id": "n3YT3gSBz",
	"name": "Muk Karai",
	"unit_id": "qkmUzGwng",
	"unit": "gm",
	"stock": -7800,
	"createdOn": {
		"$date": "2021-06-13T15:32:55Z"
	},
	"__v": 0
}
